{
  "id": "1196",
  "title": "How Many Apples Can You Put into the Basket",
  "slug": "how-many-apples-can-you-put-into-the-basket",
  "difficulty": "Easy",
  "likes": 11,
  "dislikes": 6,
  "hints": [
    "What if you think in a greedy approach?",
    "The best apple to take in one step is the one with the smallest weight.",
    "Sort the array and take apples with smaller weight first."
  ],
  "isPaidOnly": true,
  "similarQuestions": "[]",
  "solution": null,
  "topicTags": [
    "Greedy"
  ]
}